[
  {
    "description": "Como usuário, desejo acessar a Listagem\nPara que possa visualizar meus dados de cadastro",
    "keyword": "Funcionalidade",
    "name": "Listagem",
    "line": 3,
    "id": "listagem",
    "tags": [],
    "uri": "Listagem.feature",
    "elements": [
      {
        "id": "listagem;listagem-sem-registro",
        "keyword": "Scenario",
        "line": 8,
        "name": "Listagem sem registro",
        "tags": [],
        "type": "scenario",
        "steps": [
          {
            "arguments": [],
            "keyword": "Dado ",
            "line": 9,
            "name": "que o site não tenha registros",
            "result": {
              "status": "passed",
              "duration": 23019000000
            }
          },
          {
            "arguments": [],
            "keyword": "Quando ",
            "line": 10,
            "name": "acessar a listagem",
            "result": {
              "status": "passed",
              "duration": 5080000000
            }
          },
          {
            "arguments": [],
            "keyword": "Entao ",
            "line": 11,
            "name": "devo visualizar a listagem vazia",
            "result": {
              "status": "passed",
              "duration": 29000000
            }
          }
        ]
      },
      {
        "id": "listagem;listagem-com-1-registro",
        "keyword": "Scenario",
        "line": 13,
        "name": "Listagem com 1 registro",
        "tags": [],
        "type": "scenario",
        "steps": [
          {
            "arguments": [],
            "keyword": "Dado ",
            "line": 14,
            "name": "que o site possui apenas um registro",
            "result": {
              "status": "passed",
              "duration": 167000000
            }
          },
          {
            "arguments": [],
            "keyword": "Quando ",
            "line": 15,
            "name": "acessar a listagem",
            "result": {
              "status": "passed",
              "duration": 4622000000
            }
          },
          {
            "arguments": [],
            "keyword": "Entao ",
            "line": 16,
            "name": "devo visualizar apenas um registro",
            "result": {
              "status": "passed",
              "duration": 89000000
            }
          }
        ]
      }
    ]
  }
]